README.md
setup.py
google_tools/__init__.py
google_tools/currency_conversion.py
google_tools/translater.py
google_tools_wrapper.egg-info/PKG-INFO
google_tools_wrapper.egg-info/SOURCES.txt
google_tools_wrapper.egg-info/dependency_links.txt
google_tools_wrapper.egg-info/requires.txt
google_tools_wrapper.egg-info/top_level.txt