Metadata-Version: 2.1
Name: google-tools-wrapper
Version: 3.0.0
Summary: An unofficial Google Tools wrapper
Author: João Zacchello
Author-email: xongsdartx@gmail.com
License: MIT License
Keywords: google tools,google finance,google api,currency conversion,google translater,google tradutor
Requires-Dist: requests
Requires-Dist: bs4
Requires-Dist: selenium
